README.md
setup.cfg
setup.py
distributions_pdf/Binomialdistribution.py
distributions_pdf/Gaussiandistribution.py
distributions_pdf/Generaldistribution.py
distributions_pdf/__init__.py
distributions_pdf.egg-info/PKG-INFO
distributions_pdf.egg-info/SOURCES.txt
distributions_pdf.egg-info/dependency_links.txt
distributions_pdf.egg-info/not-zip-safe
distributions_pdf.egg-info/top_level.txt